lib/__init__.py
lib/exceptions.py
lib/validator.py
lib/validrequest.py
lib/version.py
validrequest/__init__.py
validrequest/exceptions.py
validrequest/validator.py
validrequest/version.py
validrequest-1.0.0.dist-info/METADATA
validrequest-1.0.0.dist-info/WHEEL
validrequest-1.0.0.dist-info/top_level.txt
validrequest-1.0.0.dist-info/RECORD
