Metadata-Version: 2.1
Name: validrequest
Version: 1.0.0
Summary: A request handler validation tool for RESTful API endpoints.
Home-page: https://github.com/ableinc/validrequest
Author: AbleInc - Jaylen Douglas
Author-email: douglas.jaylen@gmail.com
License: GNU General Public License v3 (GPLv3)
Keywords: validation tool,validation,api,restful,endpoints,ableinc
Classifier: Programming Language :: Python :: 3.6
Classifier: Programming Language :: Python :: 3.7
Classifier: Programming Language :: Python :: 3.8
Classifier: Programming Language :: Python :: 3.9
Classifier: Programming Language :: Python :: 3.10
Classifier: Programming Language :: Python :: 3.11
Classifier: Programming Language :: Python :: 3.12
Classifier: Programming Language :: Python :: 3 :: Only
Classifier: License :: OSI Approved :: GNU General Public License v3 (GPLv3)
Classifier: Operating System :: OS Independent
Requires-Dist: pypm2 ==0.2.1
Requires-Dist: twine ==4.0.2
